odoo/addons/maintenance_request_employee/README.rst
odoo/addons/maintenance_request_employee/__init__.py
odoo/addons/maintenance_request_employee/__manifest__.py
odoo/addons/maintenance_request_employee/i18n/es.po
odoo/addons/maintenance_request_employee/i18n/it.po
odoo/addons/maintenance_request_employee/i18n/maintenance_request_employee.pot
odoo/addons/maintenance_request_employee/models/__init__.py
odoo/addons/maintenance_request_employee/models/maintenance_request.py
odoo/addons/maintenance_request_employee/readme/CONTRIBUTORS.rst
odoo/addons/maintenance_request_employee/readme/DESCRIPTION.rst
odoo/addons/maintenance_request_employee/static/description/icon.png
odoo/addons/maintenance_request_employee/static/description/icon.svg
odoo/addons/maintenance_request_employee/static/description/index.html
odoo/addons/maintenance_request_employee/views/maintenance_request_views.xml
odoo13_addon_maintenance_request_employee-13.0.1.0.1.dev6.dist-info/METADATA
odoo13_addon_maintenance_request_employee-13.0.1.0.1.dev6.dist-info/WHEEL
odoo13_addon_maintenance_request_employee-13.0.1.0.1.dev6.dist-info/top_level.txt
odoo13_addon_maintenance_request_employee-13.0.1.0.1.dev6.dist-info/RECORD
